{
  "$schema": "https://developer.microsoft.com/json-schemas/fabric/item/report/definition/visualContainer/2.7.0/schema.json",
  "name": "line_ontime_trend",
  "position": {
    "x": 24,
    "y": 196,
    "z": 4,
    "height": 242,
    "width": 486,
    "tabOrder": 4
  },
  "visual": {
    "visualType": "lineChart",
    "query": {
      "queryState": {
        "Category": {
          "projections": [
            {
              "field": {
                "Column": {
                  "Expression": {
                    "SourceRef": {
                      "Entity": "DIM_DATES"
                    }
                  },
                  "Property": "MONTH_START"
                }
              },
              "queryRef": "DIM_DATES.MONTH_START",
              "nativeQueryRef": "MONTH_START",
              "active": true
            }
          ]
        },
        "Y": {
          "projections": [
            {
              "field": {
                "Measure": {
                  "Expression": {
                    "SourceRef": {
                      "Entity": "FCT_ORDERS"
                    }
                  },
                  "Property": "On-Time Delivery Rate"
                }
              },
              "queryRef": "FCT_ORDERS.On-Time Delivery Rate",
              "nativeQueryRef": "On-Time Delivery Rate"
            }
          ]
        }
      }
    },
    "drillFilterOtherVisuals": true,
    "visualContainerObjects": {
      "title": [
        {
          "properties": {
            "text": {
              "expr": {
                "Literal": {
                  "Value": "'On-time delivery rate over time'"
                }
              }
            }
          }
        }
      ]
    }
  },
  "filterConfig": {
    "filters": [
      {
        "name": "cliff_complete_months",
        "field": {
          "Column": {
            "Expression": {
              "SourceRef": {
                "Entity": "DIM_DATES"
              }
            },
            "Property": "MONTH_START"
          }
        },
        "type": "Advanced",
        "filter": {
          "Version": 2,
          "From": [
            {
              "Name": "d",
              "Entity": "DIM_DATES",
              "Type": 0
            }
          ],
          "Where": [
            {
              "Condition": {
                "Comparison": {
                  "ComparisonKind": 4,
                  "Left": {
                    "Column": {
                      "Expression": {
                        "SourceRef": {
                          "Source": "d"
                        }
                      },
                      "Property": "MONTH_START"
                    }
                  },
                  "Right": {
                    "Literal": {
                      "Value": "datetime'2018-08-31T00:00:00'"
                    }
                  }
                }
              }
            }
          ]
        }
      }
    ]
  }
}